bases/__init__.py
bases/smartbase.py
celery_smartbase-0.3.5.dist-info/LICENSE
celery_smartbase-0.3.5.dist-info/METADATA
celery_smartbase-0.3.5.dist-info/WHEEL
celery_smartbase-0.3.5.dist-info/top_level.txt
celery_smartbase-0.3.5.dist-info/RECORD
