Metadata-Version: 2.1
Name: celery-smartbase
Version: 0.3.5
Summary: An extension and improvement of the Celery package to avoid duplicate tasks and view pending tasks in Django.
Home-page: https://github.com/TonySchneider/celery-smartbase
License: UNKNOWN
Platform: UNKNOWN
Requires-Dist: Django ~=3.2.11
Requires-Dist: djangorestframework ==3.13.1
Requires-Dist: django-model-utils ==3.1.2
Requires-Dist: django-celery-results ==2.4.0
Requires-Dist: django-celery-beat ==2.2.1
Requires-Dist: kombu ~=5.2.3
Requires-Dist: celery ~=5.2.3
